f9ml/__init__.py
f9ml/data_utils/__init__.py
f9ml/data_utils/data_modules.py
f9ml/data_utils/datasets.py
f9ml/data_utils/dequantization.py
f9ml/data_utils/feature_scaling.py
f9ml/data_utils/gauss_rank_scaler.py
f9ml/data_utils/logit_transform.py
f9ml/data_utils/processors.py
f9ml/data_utils/toy_datasets.py
f9ml/models/__init__.py
f9ml/models/c2st/__init__.py
f9ml/models/c2st/c2st_pipeline.py
f9ml/models/classifiers/__init__.py
f9ml/models/classifiers/binary_model.py
f9ml/models/classifiers/multilabel_model.py
f9ml/models/flows/__init__.py
f9ml/models/flows/aux_flows.py
f9ml/models/flows/base_flows.py
f9ml/models/flows/config/README.md
f9ml/models/flows/config/glow.yaml
f9ml/models/flows/config/made_mog.yaml
f9ml/models/flows/config/maf.yaml
f9ml/models/flows/config/maf_made_mog.yaml
f9ml/models/flows/config/nice.yaml
f9ml/models/flows/config/poly_splines.yaml
f9ml/models/flows/config/realnvp.yaml
f9ml/models/flows/config/rq_splines.yaml
f9ml/models/flows/flow_utils.py
f9ml/models/flows/glow.py
f9ml/models/flows/made.py
f9ml/models/flows/made_mog.py
f9ml/models/flows/maf.py
f9ml/models/flows/mogs.py
f9ml/models/flows/nice.py
f9ml/models/flows/polynomial_splines.py
f9ml/models/flows/real_nvp.py
f9ml/models/flows/rq_splines.py
f9ml/models/flows/trackers.py
f9ml/models/gnn/__init__.py
f9ml/models/gnn/cnn.py
f9ml/models/gnn/data_utils/__init__.py
f9ml/models/gnn/data_utils/graph_data_modules.py
f9ml/models/gnn/data_utils/graph_datasets.py
f9ml/models/gnn/data_utils/graph_processors.py
f9ml/models/gnn/data_utils/graph_utils.py
f9ml/models/gnn/deep_gcn.py
f9ml/models/gnn/gnn_base.py
f9ml/models/gnn/mpnn.py
f9ml/models/gnn/sort_pool.py
f9ml/models/neural_statistician/__init__.py
f9ml/models/neural_statistician/data_modules.py
f9ml/models/neural_statistician/models.py
f9ml/models/neural_statistician/nets.py
f9ml/models/neural_statistician/trackers.py
f9ml/models/neural_statistician/utils.py
f9ml/models/np/__init__.py
f9ml/models/np/base_np.py
f9ml/models/np/cnp.py
f9ml-0.1.6.dist-info/LICENSE
f9ml-0.1.6.dist-info/METADATA
f9ml-0.1.6.dist-info/WHEEL
f9ml-0.1.6.dist-info/RECORD
