Metadata-Version: 2.1
Name: f9ml
Version: 0.1.6
Summary: JSI F9 machine learning framework.
Home-page: https://gitlab.cern.ch/ijs-f9-ljubljana/F9ML
License: MIT
Author: Jan Gavranovic
Author-email: jan.gavranovic@cern.ch
Requires-Python: >=3.11,<4.0
Classifier: License :: OSI Approved :: MIT License
Classifier: Programming Language :: Python :: 3
Classifier: Programming Language :: Python :: 3.11
Classifier: Programming Language :: Python :: 3.12
Classifier: Programming Language :: Python :: 3.13
Requires-Dist: corner (==2.2.2)
Requires-Dist: f9columnar (>=0.2.1,<0.3.0)
Requires-Dist: h5py (==3.11.0)
Requires-Dist: hydra-core (==1.3.2)
Requires-Dist: lightning (==2.4.0)
Requires-Dist: matplotlib (==3.9.2)
Requires-Dist: mlflow (==2.16.0)
Requires-Dist: networkx (==3.3)
Requires-Dist: numba (==0.60.0)
Requires-Dist: numpy (==2.0.2)
Requires-Dist: onnx (==1.16.2)
Requires-Dist: pandas (==2.2.2)
Requires-Dist: plothist (>=1.2.6,<2.0.0)
Requires-Dist: pydot (==3.0.1)
Requires-Dist: pygraphviz (==1.13)
Requires-Dist: pyqt5 (>=5.15.10,<6.0.0)
Requires-Dist: requests (>=2.28.1,<3.0.0)
Requires-Dist: rich (>=13.7.0,<14.0.0)
Requires-Dist: scikit-learn (==1.5.1)
Requires-Dist: scipy (==1.14.1)
Requires-Dist: seaborn (==0.13.2)
Requires-Dist: sympy (>=1.13.1,<2.0.0)
Requires-Dist: tables (==3.10.1)
Requires-Dist: torch (==2.4.0)
Requires-Dist: torch-geometric (==2.5.3)
Requires-Dist: torchinfo (==1.8.0)
Requires-Dist: torchmetrics (==1.4.1)
Requires-Dist: tqdm (>=4.65.0,<5.0.0)
Requires-Dist: uncertainties (==3.2.2)
Project-URL: Repository, https://gitlab.cern.ch/ijs-f9-ljubljana/F9ML
